csync/__init__.py
csync/__main__.py
csync/cli.py
csync/core.py
concurrent_sync-1.0.0.dist-info/METADATA
concurrent_sync-1.0.0.dist-info/WHEEL
concurrent_sync-1.0.0.dist-info/top_level.txt
concurrent_sync-1.0.0.dist-info/RECORD
