Metadata-Version: 2.1
Name: concurrent-sync
Version: 1.0.0
Summary: A concurrent sync tool which works with multiple sources and targets.
Home-page: https://www.github.com/simsekhalit/concurrent-sync
Author: Halit Şimşek
Author-email: mail.simsekhalit@gmail.com
License: MIT
Keywords: archive,backup,buffer,concurrent,csync,rsync,sync,synchronization
Platform: UNKNOWN
Classifier: Development Status :: 5 - Production/Stable
Classifier: License :: OSI Approved :: MIT License
Classifier: Programming Language :: Python
Classifier: Programming Language :: Python :: 3
Classifier: Programming Language :: Python :: 3.8
Classifier: Programming Language :: Python :: 3.9
Classifier: Programming Language :: Python :: 3.10
Classifier: Programming Language :: Python :: 3.11
Classifier: Programming Language :: Python :: Implementation :: CPython
Classifier: Programming Language :: Python :: Implementation :: PyPy
Classifier: Topic :: System :: Archiving :: Backup
Requires-Python: >=3.8
Requires-Dist: psutil
